godaddypy_cli/__init__.py
godaddypy_cli/__main__.py
godaddypy_cli/cli.py
godaddypy_cli-0.1.4.dist-info/licenses/LICENSE
godaddypy_cli-0.1.4.dist-info/METADATA
godaddypy_cli-0.1.4.dist-info/WHEEL
godaddypy_cli-0.1.4.dist-info/entry_points.txt
godaddypy_cli-0.1.4.dist-info/top_level.txt
godaddypy_cli-0.1.4.dist-info/RECORD
