Metadata-Version: 2.4
Name: godaddypy-cli
Version: 0.1.4
Summary: Beautiful Command Line Interface for GoDaddy API using GoDaddyPy
Author-email: Connor O'Dea <cpodea5@gmail.com>
License: MIT
Project-URL: Homepage, https://github.com/connorodea/godaddypy-cli
Project-URL: Bug Tracker, https://github.com/connorodea/godaddypy-cli/issues
Keywords: godaddy,dns,api,cli,domains
Classifier: Development Status :: 3 - Alpha
Classifier: Intended Audience :: Developers
Classifier: License :: OSI Approved :: MIT License
Classifier: Programming Language :: Python :: 3
Classifier: Programming Language :: Python :: 3.7
Classifier: Programming Language :: Python :: 3.8
Classifier: Programming Language :: Python :: 3.9
Classifier: Programming Language :: Python :: 3.10
Requires-Python: >=3.7
License-File: LICENSE
Requires-Dist: godaddypy>=2.5.1
Requires-Dist: rich>=12.0.0
Requires-Dist: pyyaml>=6.0
Requires-Dist: configloader>=1.0.1
Dynamic: license-file
